[{"dt": 1615636800, "temp": 10.03, "humidity": 77}, {"dt": 1615647600, "temp": 10.36, "humidity": 65}, {"dt": 1615658400, "temp": 7.62, "humidity": 84}, {"dt": 1615669200, "temp": 5.43, "humidity": 86}, {"dt": 1615680000, "temp": 3.67, "humidity": 86}, {"dt": 1615690800, "temp": 2.42, "humidity": 86}, {"dt": 1615701600, "temp": 1.65, "humidity": 87}, {"dt": 1615712400, "temp": 6.91, "humidity": 72}, {"dt": 1615723200, "temp": 9.53, "humidity": 62}, {"dt": 1615734000, "temp": 9.62, "humidity": 63}, {"dt": 1615744800, "temp": 6.72, "humidity": 80}, {"dt": 1615755600, "temp": 4.62, "humidity": 89}, {"dt": 1615766400, "temp": 3.81, "humidity": 91}, {"dt": 1615777200, "temp": 3.74, "humidity": 90}, {"dt": 1615788000, "temp": 5.69, "humidity": 88}, {"dt": 1615798800, "temp": 8.27, "humidity": 89}, {"dt": 1615809600, "temp": 12.02, "humidity": 71}, {"dt": 1615820400, "temp": 12.35, "humidity": 71}, {"dt": 1615831200, "temp": 9.31, "humidity": 82}, {"dt": 1615842000, "temp": 6.69, "humidity": 92}, {"dt": 1615852800, "temp": 6.96, "humidity": 92}, {"dt": 1615863600, "temp": 4.18, "humidity": 96}, {"dt": 1615874400, "temp": 2.56, "humidity": 94}, {"dt": 1615885200, "temp": 6.67, "humidity": 71}, {"dt": 1615896000, "temp": 9.8, "humidity": 57}, {"dt": 1615906800, "temp": 9.96, "humidity": 58}, {"dt": 1615917600, "temp": 5.7, "humidity": 77}, {"dt": 1615928400, "temp": 3.25, "humidity": 81}, {"dt": 1615939200, "temp": 1.94, "humidity": 86}, {"dt": 1615950000, "temp": 0.56, "humidity": 92}, {"dt": 1615960800, "temp": -0.49, "humidity": 92}, {"dt": 1615971600, "temp": 5.33, "humidity": 69}, {"dt": 1615982400, "temp": 8.32, "humidity": 70}, {"dt": 1615993200, "temp": 8.26, "humidity": 72}, {"dt": 1616004000, "temp": 5.44, "humidity": 79}, {"dt": 1616014800, "temp": 2.85, "humidity": 89}, {"dt": 1616025600, "temp": 1.55, "humidity": 89}, {"dt": 1616036400, "temp": 0.45, "humidity": 94}, {"dt": 1616047200, "temp": 1.32, "humidity": 93}, {"dt": 1616058000, "temp": 4.86, "humidity": 73}]