[{"dt": 1622678400, "temp": 16.85, "humidity": 69}, {"dt": 1622689200, "temp": 15.5, "humidity": 82}, {"dt": 1622700000, "temp": 16.75, "humidity": 88}, {"dt": 1622710800, "temp": 21.78, "humidity": 65}, {"dt": 1622721600, "temp": 24.98, "humidity": 56}, {"dt": 1622732400, "temp": 26.11, "humidity": 55}, {"dt": 1622743200, "temp": 22.7, "humidity": 79}, {"dt": 1622754000, "temp": 17.04, "humidity": 97}, {"dt": 1622764800, "temp": 15.64, "humidity": 98}, {"dt": 1622775600, "temp": 15.05, "humidity": 98}, {"dt": 1622786400, "temp": 14.62, "humidity": 97}, {"dt": 1622797200, "temp": 15.21, "humidity": 92}, {"dt": 1622808000, "temp": 15.14, "humidity": 92}, {"dt": 1622818800, "temp": 17.24, "humidity": 81}, {"dt": 1622829600, "temp": 16.82, "humidity": 80}, {"dt": 1622840400, "temp": 15.09, "humidity": 84}, {"dt": 1622851200, "temp": 11.69, "humidity": 90}, {"dt": 1622862000, "temp": 9.26, "humidity": 87}, {"dt": 1622872800, "temp": 10.74, "humidity": 77}, {"dt": 1622883600, "temp": 16.52, "humidity": 51}, {"dt": 1622894400, "temp": 20.2, "humidity": 47}, {"dt": 1622905200, "temp": 21.45, "humidity": 51}, {"dt": 1622916000, "temp": 18.9, "humidity": 75}, {"dt": 1622926800, "temp": 14.05, "humidity": 93}, {"dt": 1622937600, "temp": 13.62, "humidity": 93}, {"dt": 1622948400, "temp": 13.88, "humidity": 90}, {"dt": 1622959200, "temp": 14.07, "humidity": 80}, {"dt": 1622970000, "temp": 16.99, "humidity": 74}, {"dt": 1622980800, "temp": 21.11, "humidity": 63}, {"dt": 1622991600, "temp": 22.2, "humidity": 57}, {"dt": 1623002400, "temp": 20.63, "humidity": 64}, {"dt": 1623013200, "temp": 15.35, "humidity": 78}, {"dt": 1623024000, "temp": 13.25, "humidity": 89}, {"dt": 1623034800, "temp": 12.15, "humidity": 94}, {"dt": 1623045600, "temp": 14.69, "humidity": 86}, {"dt": 1623056400, "temp": 19.94, "humidity": 64}, {"dt": 1623067200, "temp": 22.77, "humidity": 53}, {"dt": 1623078000, "temp": 23.7, "humidity": 52}, {"dt": 1623088800, "temp": 21.73, "humidity": 63}, {"dt": 1623099600, "temp": 16.57, "humidity": 81}]