[{"dt": 1614546000, "temp": 7.29, "humidity": 74}, {"dt": 1614556800, "temp": 5.69, "humidity": 83}, {"dt": 1614567600, "temp": 4.89, "humidity": 88}, {"dt": 1614578400, "temp": 4.88, "humidity": 87}, {"dt": 1614589200, "temp": 8.87, "humidity": 74}, {"dt": 1614600000, "temp": 14.23, "humidity": 55}, {"dt": 1614610800, "temp": 15.6, "humidity": 51}, {"dt": 1614621600, "temp": 10.47, "humidity": 68}, {"dt": 1614632400, "temp": 8.63, "humidity": 81}, {"dt": 1614643200, "temp": 7.64, "humidity": 84}, {"dt": 1614654000, "temp": 6.01, "humidity": 78}, {"dt": 1614664800, "temp": 5.18, "humidity": 74}, {"dt": 1614675600, "temp": 9.65, "humidity": 61}, {"dt": 1614686400, "temp": 14.48, "humidity": 58}, {"dt": 1614697200, "temp": 15.43, "humidity": 60}, {"dt": 1614708000, "temp": 10.81, "humidity": 81}, {"dt": 1614718800, "temp": 9.42, "humidity": 85}, {"dt": 1614729600, "temp": 8.53, "humidity": 90}, {"dt": 1614740400, "temp": 7.52, "humidity": 87}, {"dt": 1614751200, "temp": 8.04, "humidity": 85}, {"dt": 1614762000, "temp": 9.68, "humidity": 83}, {"dt": 1614772800, "temp": 13.0, "humidity": 76}, {"dt": 1614783600, "temp": 14.65, "humidity": 72}, {"dt": 1614794400, "temp": 11.37, "humidity": 88}, {"dt": 1614805200, "temp": 9.48, "humidity": 91}, {"dt": 1614816000, "temp": 9.19, "humidity": 92}, {"dt": 1614826800, "temp": 7.75, "humidity": 92}, {"dt": 1614837600, "temp": 5.91, "humidity": 90}, {"dt": 1614848400, "temp": 9.48, "humidity": 79}, {"dt": 1614859200, "temp": 11.76, "humidity": 75}, {"dt": 1614870000, "temp": 11.58, "humidity": 75}, {"dt": 1614880800, "temp": 9.08, "humidity": 80}, {"dt": 1614891600, "temp": 6.77, "humidity": 87}, {"dt": 1614902400, "temp": 5.59, "humidity": 93}, {"dt": 1614913200, "temp": 4.89, "humidity": 96}, {"dt": 1614924000, "temp": 5.59, "humidity": 92}, {"dt": 1614934800, "temp": 6.79, "humidity": 86}, {"dt": 1614945600, "temp": 7.94, "humidity": 77}, {"dt": 1614956400, "temp": 8.42, "humidity": 73}, {"dt": 1614967200, "temp": 6.52, "humidity": 73}]