[{"dt": 1622228400, "temp": 292.22, "humidity": 50}, {"dt": 1622232000, "temp": 291.85, "humidity": 54}, {"dt": 1622235600, "temp": 291.23, "humidity": 59}, {"dt": 1622239200, "temp": 290.17, "humidity": 67}, {"dt": 1622242800, "temp": 289.11, "humidity": 75}, {"dt": 1622246400, "temp": 287.49, "humidity": 84}, {"dt": 1622250000, "temp": 286.03, "humidity": 90}, {"dt": 1622253600, "temp": 285.13, "humidity": 92}, {"dt": 1622257200, "temp": 284.49, "humidity": 92}, {"dt": 1622260800, "temp": 283.98, "humidity": 93}, {"dt": 1622264400, "temp": 284.27, "humidity": 92}, {"dt": 1622268000, "temp": 286.32, "humidity": 84}, {"dt": 1622271600, "temp": 288.41, "humidity": 76}, {"dt": 1622275200, "temp": 290.2, "humidity": 68}, {"dt": 1622278800, "temp": 291.75, "humidity": 61}, {"dt": 1622282400, "temp": 293.01, "humidity": 55}, {"dt": 1622286000, "temp": 293.77, "humidity": 51}, {"dt": 1622289600, "temp": 294.41, "humidity": 49}, {"dt": 1622293200, "temp": 294.85, "humidity": 48}, {"dt": 1622296800, "temp": 295.18, "humidity": 47}, {"dt": 1622300400, "temp": 295.09, "humidity": 47}, {"dt": 1622304000, "temp": 294.77, "humidity": 48}, {"dt": 1622307600, "temp": 294.28, "humidity": 55}, {"dt": 1622311200, "temp": 292.85, "humidity": 62}, {"dt": 1622314800, "temp": 290.43, "humidity": 72}, {"dt": 1622318400, "temp": 288.35, "humidity": 78}, {"dt": 1622322000, "temp": 287.18, "humidity": 83}, {"dt": 1622325600, "temp": 286.13, "humidity": 86}, {"dt": 1622329200, "temp": 285.15, "humidity": 89}, {"dt": 1622332800, "temp": 284.68, "humidity": 90}, {"dt": 1622336400, "temp": 284.18, "humidity": 92}, {"dt": 1622340000, "temp": 283.76, "humidity": 93}, {"dt": 1622343600, "temp": 283.35, "humidity": 94}, {"dt": 1622347200, "temp": 283.05, "humidity": 94}, {"dt": 1622350800, "temp": 283.52, "humidity": 91}, {"dt": 1622354400, "temp": 285.5, "humidity": 82}, {"dt": 1622358000, "temp": 287.35, "humidity": 70}, {"dt": 1622361600, "temp": 289.11, "humidity": 63}, {"dt": 1622365200, "temp": 290.73, "humidity": 58}, {"dt": 1622368800, "temp": 292.31, "humidity": 54}, {"dt": 1622372400, "temp": 293.5, "humidity": 49}, {"dt": 1622376000, "temp": 294.28, "humidity": 45}, {"dt": 1622379600, "temp": 294.65, "humidity": 42}, {"dt": 1622383200, "temp": 294.69, "humidity": 42}, {"dt": 1622386800, "temp": 294.57, "humidity": 43}, {"dt": 1622390400, "temp": 294.17, "humidity": 46}, {"dt": 1622394000, "temp": 293.73, "humidity": 55}, {"dt": 1622397600, "temp": 292.48, "humidity": 60}]