[{"dt": 1624665600, "temp": 288.28, "humidity": 88, "pressure": 1018, "clouds": 0, "wind_speed": 1.03, "wind_deg": 290, "description": "clear sky"}, {"dt": 1624669200, "temp": 288.19, "humidity": 88, "pressure": 1018, "clouds": 75, "wind_speed": 0.51, "wind_deg": 310, "description": "broken clouds"}, {"dt": 1624672800, "temp": 288, "humidity": 88, "pressure": 1018, "clouds": 0, "wind_speed": 0.62, "wind_deg": 16, "description": "clear sky"}, {"dt": 1624676400, "temp": 287.94, "humidity": 88, "pressure": 1017, "clouds": 0, "wind_speed": 1.03, "wind_deg": 320, "description": "clear sky"}, {"dt": 1624680000, "temp": 287.56, "humidity": 94, "pressure": 1017, "clouds": 0, "wind_speed": 1.03, "wind_deg": 0, "description": "clear sky"}, {"dt": 1624683600, "temp": 287.72, "humidity": 88, "pressure": 1017, "clouds": 90, "wind_speed": 1.54, "wind_deg": 310, "description": "overcast clouds"}, {"dt": 1624687200, "temp": 288.42, "humidity": 94, "pressure": 1017, "clouds": 90, "wind_speed": 1.54, "wind_deg": 20, "description": "overcast clouds"}, {"dt": 1624690800, "temp": 290.51, "humidity": 82, "pressure": 1017, "clouds": 75, "wind_speed": 2.57, "wind_deg": 70, "description": "broken clouds"}, {"dt": 1624694400, "temp": 292.3, "humidity": 77, "pressure": 1016, "clouds": 75, "wind_speed": 2.57, "wind_deg": 130, "description": "broken clouds"}, {"dt": 1624698000, "temp": 293.52, "humidity": 73, "pressure": 1016, "clouds": 75, "wind_speed": 2.06, "wind_deg": 80, "description": "broken clouds"}, {"dt": 1624701600, "temp": 294.74, "humidity": 64, "pressure": 1015, "clouds": 75, "wind_speed": 2.57, "wind_deg": 150, "description": "broken clouds"}, {"dt": 1624705200, "temp": 296.22, "humidity": 53, "pressure": 1015, "clouds": 75, "wind_speed": 2.57, "wind_deg": 160, "description": "broken clouds"}, {"dt": 1624708800, "temp": 296.9, "humidity": 49, "pressure": 1014, "clouds": 75, "wind_speed": 3.6, "wind_deg": 140, "description": "broken clouds"}, {"dt": 1624712400, "temp": 297.11, "humidity": 49, "pressure": 1014, "clouds": 0, "wind_speed": 3.09, "wind_deg": 120, "description": "clear sky"}, {"dt": 1624716000, "temp": 297.03, "humidity": 46, "pressure": 1013, "clouds": 0, "wind_speed": 3.09, "wind_deg": 150, "description": "clear sky"}, {"dt": 1624719600, "temp": 297.72, "humidity": 46, "pressure": 1013, "clouds": 0, "wind_speed": 3.09, "wind_deg": 150, "description": "clear sky"}, {"dt": 1624723200, "temp": 298.29, "humidity": 46, "pressure": 1013, "clouds": 0, "wind_speed": 2.57, "wind_deg": 170, "description": "clear sky"}, {"dt": 1624726800, "temp": 297.93, "humidity": 50, "pressure": 1012, "clouds": 0, "wind_speed": 1.54, "wind_deg": 0, "description": "clear sky"}, {"dt": 1624730400, "temp": 297.6, "humidity": 50, "pressure": 1012, "clouds": 0, "wind_speed": 2.06, "wind_deg": 140, "description": "clear sky"}, {"dt": 1624734000, "temp": 295.39, "humidity": 49, "pressure": 1011, "clouds": 0, "wind_speed": 2.06, "wind_deg": 140, "description": "clear sky"}, {"dt": 1624737600, "temp": 294.02, "humidity": 53, "pressure": 1012, "clouds": 0, "wind_speed": 1.03, "wind_deg": 0, "description": "clear sky"}, {"dt": 1624741200, "temp": 293.17, "humidity": 56, "pressure": 1013, "clouds": 0, "wind_speed": 1.03, "wind_deg": 80, "description": "clear sky"}, {"dt": 1624744800, "temp": 292.4, "humidity": 64, "pressure": 1012, "clouds": 0, "wind_speed": 1.54, "wind_deg": 80, "description": "clear sky"}, {"dt": 1624748400, "temp": 292.48, "humidity": 64, "pressure": 1012, "clouds": 100, "wind_speed": 1.54, "wind_deg": 0, "description": "light rain"}]