[{"dt": 1614729600, "temp": 280.14, "humidity": 76, "pressure": 1029, "clouds": 0, "wind_speed": 2.06, "wind_deg": 160, "description": "clear sky"}, {"dt": 1614733200, "temp": 280.68, "humidity": 76, "pressure": 1029, "clouds": 0, "wind_speed": 2.57, "wind_deg": 170, "description": "clear sky"}, {"dt": 1614736800, "temp": 280.34, "humidity": 70, "pressure": 1029, "clouds": 0, "wind_speed": 3.09, "wind_deg": 190, "description": "clear sky"}, {"dt": 1614740400, "temp": 280.34, "humidity": 70, "pressure": 1029, "clouds": 0, "wind_speed": 2.06, "wind_deg": 190, "description": "clear sky"}, {"dt": 1614744000, "temp": 280, "humidity": 70, "pressure": 1029, "clouds": 0, "wind_speed": 1.03, "wind_deg": 0, "description": "clear sky"}, {"dt": 1614747600, "temp": 280.2, "humidity": 70, "pressure": 1029, "clouds": 0, "wind_speed": 2.06, "wind_deg": 150, "description": "clear sky"}, {"dt": 1614751200, "temp": 279.36, "humidity": 75, "pressure": 1029, "clouds": 0, "wind_speed": 1.54, "wind_deg": 180, "description": "clear sky"}, {"dt": 1614754800, "temp": 280.34, "humidity": 70, "pressure": 1029, "clouds": 0, "wind_speed": 2.57, "wind_deg": 150, "description": "clear sky"}, {"dt": 1614758400, "temp": 280.34, "humidity": 76, "pressure": 1030, "clouds": 0, "wind_speed": 1.54, "wind_deg": 180, "description": "clear sky"}, {"dt": 1614762000, "temp": 283.11, "humidity": 57, "pressure": 1034, "clouds": 0, "wind_speed": 3.09, "wind_deg": 190, "description": "clear sky"}, {"dt": 1614765600, "temp": 285.52, "humidity": 62, "pressure": 1034, "clouds": 0, "wind_speed": 4.12, "wind_deg": 180, "description": "clear sky"}, {"dt": 1614769200, "temp": 287.67, "humidity": 58, "pressure": 1034, "clouds": 0, "wind_speed": 3.09, "wind_deg": 160, "description": "clear sky"}, {"dt": 1614772800, "temp": 288.84, "humidity": 58, "pressure": 1034, "clouds": 0, "wind_speed": 3.09, "wind_deg": 170, "description": "clear sky"}, {"dt": 1614776400, "temp": 289.53, "humidity": 51, "pressure": 1033, "clouds": 0, "wind_speed": 3.6, "wind_deg": 170, "description": "clear sky"}, {"dt": 1614780000, "temp": 290.17, "humidity": 55, "pressure": 1032, "clouds": 0, "wind_speed": 3.6, "wind_deg": 210, "description": "clear sky"}, {"dt": 1614783600, "temp": 290.27, "humidity": 55, "pressure": 1032, "clouds": 0, "wind_speed": 3.6, "wind_deg": 230, "description": "clear sky"}, {"dt": 1614787200, "temp": 290.41, "humidity": 55, "pressure": 1031, "clouds": 0, "wind_speed": 2.06, "wind_deg": 260, "description": "clear sky"}, {"dt": 1614790800, "temp": 288.79, "humidity": 63, "pressure": 1031, "clouds": 0, "wind_speed": 2.57, "wind_deg": 240, "description": "clear sky"}, {"dt": 1614794400, "temp": 287.96, "humidity": 58, "pressure": 1031, "clouds": 90, "wind_speed": 1.03, "wind_deg": 240, "description": "overcast clouds"}, {"dt": 1614798000, "temp": 286.15, "humidity": 76, "pressure": 1026, "clouds": 90, "wind_speed": 1.03, "wind_deg": 350, "description": "overcast clouds"}, {"dt": 1614801600, "temp": 285.29, "humidity": 82, "pressure": 1033, "clouds": 90, "wind_speed": 2.57, "wind_deg": 320, "description": "overcast clouds"}, {"dt": 1614805200, "temp": 284.36, "humidity": 87, "pressure": 1033, "clouds": 0, "wind_speed": 2.06, "wind_deg": 320, "description": "clear sky"}, {"dt": 1614808800, "temp": 283.67, "humidity": 82, "pressure": 1033, "clouds": 75, "wind_speed": 1.03, "wind_deg": 310, "description": "broken clouds"}, {"dt": 1614812400, "temp": 283.05, "humidity": 87, "pressure": 1031, "clouds": 90, "wind_speed": 0.51, "wind_deg": 270, "description": "overcast clouds"}]