{"lat": 46.6507, "lon": 0.3748, "timezone": "Europe/Paris", "timezone_offset": 3600, "current": {"dt": 1615140000, "sunrise": 1615098413, "sunset": 1615139544, "temp": 282.03, "feels_like": 277.8, "pressure": 1025, "humidity": 61, "dew_point": 274.93, "clouds": 0, "visibility": 10000, "wind_speed": 3.6, "wind_deg": 10, "weather": [{"id": 800, "main": "Clear", "description": "clear sky", "icon": "01n"}]}, "hourly": [{"dt": 1615075200, "temp": 276.37, "feels_like": 272.11, "pressure": 1030, "humidity": 75, "dew_point": 272.46, "clouds": 40, "visibility": 10000, "wind_speed": 3.09, "wind_deg": 10, "weather": [{"id": 802, "main": "Clouds", "description": "scattered clouds", "icon": "03n"}]}, {"dt": 1615078800, "temp": 276.52, "feels_like": 272.52, "pressure": 1030, "humidity": 70, "dew_point": 271.76, "clouds": 90, "visibility": 10000, "wind_speed": 2.57, "wind_deg": 20, "weather": [{"id": 804, "main": "Clouds", "description": "overcast clouds", "icon": "04n"}]}, {"dt": 1615082400, "temp": 276.71, "feels_like": 273.45, "pressure": 1029, "humidity": 70, "dew_point": 271.92, "clouds": 90, "visibility": 10000, "wind_speed": 1.54, "wind_deg": 10, "weather": [{"id": 804, "main": "Clouds", "description": "overcast clouds", "icon": "04n"}]}, {"dt": 1615086000, "temp": 276.71, "feels_like": 273.68, "pressure": 1029, "humidity": 65, "dew_point": 271.03, "clouds": 0, "visibility": 10000, "wind_speed": 1.03, "wind_deg": 50, "weather": [{"id": 800, "main": "Clear", "description": "clear sky", "icon": "01n"}]}, {"dt": 1615089600, "temp": 276.37, "feels_like": 272.83, "pressure": 1029, "humidity": 75, "dew_point": 272.46, "clouds": 90, "visibility": 10000, "wind_speed": 2.06, "wind_deg": 10, "weather": [{"id": 804, "main": "Clouds", "description": "overcast clouds", "icon": "04n"}]}, {"dt": 1615093200, "temp": 276.31, "feels_like": 272.76, "pressure": 1032, "humidity": 75, "dew_point": 272.41, "clouds": 90, "visibility": 10000, "wind_speed": 2.06, "wind_deg": 10, "weather": [{"id": 804, "main": "Clouds", "description": "overcast clouds", "icon": "04n"}]}, {"dt": 1615096800, "temp": 276.15, "feels_like": 272.95, "pressure": 1023, "humidity": 75, "dew_point": 272.28, "clouds": 90, "visibility": 10000, "wind_speed": 1.54, "wind_deg": 350, "weather": [{"id": 804, "main": "Clouds", "description": "overcast clouds", "icon": "04n"}]}, {"dt": 1615100400, "temp": 276.31, "feels_like": 272.76, "pressure": 1031, "humidity": 75, "dew_point": 272.41, "clouds": 90, "visibility": 10000, "wind_speed": 2.06, "wind_deg": 360, "weather": [{"id": 804, "main": "Clouds", "description": "overcast clouds", "icon": "04d"}]}, {"dt": 1615104000, "temp": 276.98, "feels_like": 273.76, "pressure": 1028, "humidity": 70, "dew_point": 272.15, "clouds": 90, "visibility": 10000, "wind_speed": 1.54, "wind_deg": 20, "weather": [{"id": 804, "main": "Clouds", "description": "overcast clouds", "icon": "04d"}]}, {"dt": 1615107600, "temp": 277.78, "feels_like": 274.3, "pressure": 1028, "humidity": 70, "dew_point": 272.83, "clouds": 90, "visibility": 10000, "wind_speed": 2.06, "wind_deg": 30, "weather": [{"id": 804, "main": "Clouds", "description": "overcast clouds", "icon": "04d"}]}, {"dt": 1615111200, "temp": 279.74, "feels_like": 276.75, "pressure": 1028, "humidity": 65, "dew_point": 273.64, "clouds": 0, "visibility": 10000, "wind_speed": 1.54, "wind_deg": 0, "weather": [{"id": 800, "main": "Clear", "description": "clear sky", "icon": "01d"}]}, {"dt": 1615114800, "temp": 281.74, "feels_like": 278.19, "pressure": 1027, "humidity": 61, "dew_point": 274.65, "clouds": 0, "visibility": 10000, "wind_speed": 2.57, "wind_deg": 10, "weather": [{"id": 800, "main": "Clear", "description": "clear sky", "icon": "01d"}]}, {"dt": 1615118400, "temp": 282.71, "feels_like": 278.59, "pressure": 1027, "humidity": 61, "dew_point": 275.57, "clouds": 0, "visibility": 10000, "wind_speed": 3.6, "wind_deg": 350, "weather": [{"id": 800, "main": "Clear", "description": "clear sky", "icon": "01d"}]}, {"dt": 1615122000, "temp": 283.24, "feels_like": 279.76, "pressure": 1026, "humidity": 57, "dew_point": 275.12, "clouds": 0, "visibility": 10000, "wind_speed": 2.57, "wind_deg": 50, "weather": [{"id": 800, "main": "Clear", "description": "clear sky", "icon": "01d"}]}, {"dt": 1615125600, "temp": 283.4, "feels_like": 279.95, "pressure": 1026, "humidity": 57, "dew_point": 275.27, "clouds": 90, "visibility": 10000, "wind_speed": 2.57, "wind_deg": 360, "weather": [{"id": 804, "main": "Clouds", "description": "overcast clouds", "icon": "04d"}]}, {"dt": 1615129200, "temp": 283.41, "feels_like": 278.87, "pressure": 1025, "humidity": 57, "dew_point": 275.28, "clouds": 90, "visibility": 10000, "wind_speed": 4.12, "wind_deg": 20, "weather": [{"id": 804, "main": "Clouds", "description": "overcast clouds", "icon": "04d"}]}, {"dt": 1615132800, "temp": 283.15, "feels_like": 278.94, "pressure": 1025, "humidity": 57, "dew_point": 275.03, "clouds": 90, "visibility": 10000, "wind_speed": 3.6, "wind_deg": 10, "weather": [{"id": 804, "main": "Clouds", "description": "overcast clouds", "icon": "04d"}]}, {"dt": 1615136400, "temp": 282.47, "feels_like": 277.94, "pressure": 1024, "humidity": 61, "dew_point": 275.34, "clouds": 0, "visibility": 10000, "wind_speed": 4.12, "wind_deg": 20, "weather": [{"id": 800, "main": "Clear", "description": "clear sky", "icon": "01d"}]}, {"dt": 1615140000, "temp": 282.03, "feels_like": 277.8, "pressure": 1025, "humidity": 61, "dew_point": 274.93, "clouds": 0, "visibility": 10000, "wind_speed": 3.6, "wind_deg": 10, "weather": [{"id": 800, "main": "Clear", "description": "clear sky", "icon": "01n"}]}, {"dt": 1615143600, "temp": 281.35, "feels_like": 277.92, "pressure": 1025, "humidity": 66, "dew_point": 275.38, "clouds": 0, "visibility": 10000, "wind_speed": 2.57, "wind_deg": 10, "weather": [{"id": 800, "main": "Clear", "description": "clear sky", "icon": "01n"}]}, {"dt": 1615147200, "temp": 280.81, "feels_like": 278.15, "pressure": 1025, "humidity": 70, "dew_point": 275.69, "clouds": 0, "visibility": 10000, "wind_speed": 1.54, "wind_deg": 360, "weather": [{"id": 800, "main": "Clear", "description": "clear sky", "icon": "01n"}]}, {"dt": 1615150800, "temp": 280.66, "feels_like": 277.61, "pressure": 1025, "humidity": 70, "dew_point": 275.55, "clouds": 90, "visibility": 10000, "wind_speed": 2.06, "wind_deg": 360, "weather": [{"id": 804, "main": "Clouds", "description": "overcast clouds", "icon": "04n"}]}, {"dt": 1615154400, "temp": 280.41, "feels_like": 276.43, "pressure": 1026, "humidity": 65, "dew_point": 274.28, "clouds": 90, "visibility": 10000, "wind_speed": 3.09, "wind_deg": 20, "weather": [{"id": 804, "main": "Clouds", "description": "overcast clouds", "icon": "04n"}]}, {"dt": 1615158000, "temp": 279.91, "feels_like": 274.52, "pressure": 1026, "humidity": 57, "dew_point": 272.13, "clouds": 0, "visibility": 10000, "wind_speed": 4.63, "wind_deg": 30, "weather": [{"id": 800, "main": "Clear", "description": "clear sky", "icon": "01n"}]}]}