{"lat": 46.6507, "lon": 0.3748, "timezone": "Europe/Paris", "timezone_offset": 7200, "current": {"dt": 1623171600, "sunrise": 1623125140, "sunset": 1623181784, "temp": 299.26, "feels_like": 298.69, "pressure": 1019, "humidity": 47, "dew_point": 287.08, "uvi": 7.76, "clouds": 0, "visibility": 10000, "wind_speed": 2.57, "wind_deg": 10, "weather": [{"id": 800, "main": "Clear", "description": "clear sky", "icon": "01d"}]}, "hourly": [{"dt": 1623110400, "temp": 288.53, "feels_like": 288.17, "pressure": 1020, "humidity": 82, "dew_point": 285.48, "clouds": 0, "visibility": 10000, "wind_speed": 1.54, "wind_deg": 200, "weather": [{"id": 800, "main": "Clear", "description": "clear sky", "icon": "01n"}]}, {"dt": 1623114000, "temp": 287.64, "feels_like": 287.7, "pressure": 1020, "humidity": 88, "dew_point": 285.68, "clouds": 0, "visibility": 10000, "wind_speed": 1.03, "wind_deg": 170, "weather": [{"id": 800, "main": "Clear", "description": "clear sky", "icon": "01n"}]}, {"dt": 1623117600, "temp": 286.52, "feels_like": 286.38, "pressure": 1020, "humidity": 94, "dew_point": 285.58, "clouds": 0, "visibility": 10000, "wind_speed": 1.27, "wind_deg": 345, "wind_gust": 1.35, "weather": [{"id": 800, "main": "Clear", "description": "clear sky", "icon": "01n"}]}, {"dt": 1623121200, "temp": 285.85, "feels_like": 285.34, "pressure": 1020, "humidity": 94, "dew_point": 284.91, "clouds": 0, "visibility": 10000, "wind_speed": 1.51, "wind_deg": 6, "wind_gust": 1.53, "weather": [{"id": 800, "main": "Clear", "description": "clear sky", "icon": "01n"}]}, {"dt": 1623124800, "temp": 285.44, "feels_like": 285.15, "pressure": 1020, "humidity": 94, "dew_point": 284.5, "clouds": 0, "visibility": 10000, "wind_speed": 1.03, "wind_deg": 320, "weather": [{"id": 800, "main": "Clear", "description": "clear sky", "icon": "01n"}]}, {"dt": 1623128400, "temp": 286.13, "feels_like": 285.87, "pressure": 1021, "humidity": 94, "dew_point": 285.19, "clouds": 0, "visibility": 10000, "wind_speed": 1.28, "wind_deg": 48, "wind_gust": 1.28, "weather": [{"id": 800, "main": "Clear", "description": "clear sky", "icon": "01d"}]}, {"dt": 1623132000, "temp": 289.13, "feels_like": 290.03, "pressure": 1021, "humidity": 94, "dew_point": 288.17, "clouds": 0, "visibility": 10000, "wind_speed": 1.03, "wind_deg": 0, "weather": [{"id": 800, "main": "Clear", "description": "clear sky", "icon": "01d"}]}, {"dt": 1623135600, "temp": 291.61, "feels_like": 292.29, "pressure": 1023, "humidity": 72, "dew_point": 286.47, "clouds": 0, "visibility": 10000, "wind_speed": 0.51, "wind_deg": 0, "weather": [{"id": 800, "main": "Clear", "description": "clear sky", "icon": "01d"}]}, {"dt": 1623139200, "temp": 294.76, "feels_like": 294.44, "pressure": 1023, "humidity": 56, "dew_point": 285.62, "clouds": 0, "visibility": 10000, "wind_speed": 1.54, "wind_deg": 80, "weather": [{"id": 800, "main": "Clear", "description": "clear sky", "icon": "01d"}]}, {"dt": 1623142800, "temp": 296.75, "feels_like": 296, "pressure": 1023, "humidity": 49, "dew_point": 285.42, "clouds": 0, "visibility": 10000, "wind_speed": 2.06, "wind_deg": 60, "weather": [{"id": 800, "main": "Clear", "description": "clear sky", "icon": "01d"}]}, {"dt": 1623146400, "temp": 297.35, "feels_like": 296.88, "pressure": 1023, "humidity": 50, "dew_point": 286.28, "clouds": 20, "visibility": 10000, "wind_speed": 2.06, "wind_deg": 30, "weather": [{"id": 801, "main": "Clouds", "description": "few clouds", "icon": "02d"}]}, {"dt": 1623150000, "temp": 297.69, "feels_like": 298, "pressure": 1020, "humidity": 46, "dew_point": 285.32, "clouds": 0, "visibility": 10000, "wind_speed": 0.51, "wind_deg": 320, "weather": [{"id": 800, "main": "Clear", "description": "clear sky", "icon": "01d"}]}, {"dt": 1623153600, "temp": 298.72, "feels_like": 298.6, "pressure": 1020, "humidity": 46, "dew_point": 286.25, "clouds": 0, "visibility": 10000, "wind_speed": 1.54, "wind_deg": 0, "weather": [{"id": 800, "main": "Clear", "description": "clear sky", "icon": "01d"}]}, {"dt": 1623157200, "temp": 298.62, "feels_like": 297.17, "pressure": 1019, "humidity": 44, "dew_point": 285.49, "clouds": 0, "visibility": 10000, "wind_speed": 3.09, "wind_deg": 40, "weather": [{"id": 800, "main": "Clear", "description": "clear sky", "icon": "01d"}]}, {"dt": 1623160800, "temp": 299.04, "feels_like": 298.43, "pressure": 1019, "humidity": 44, "dew_point": 285.87, "clouds": 0, "visibility": 10000, "wind_speed": 2.06, "wind_deg": 360, "weather": [{"id": 800, "main": "Clear", "description": "clear sky", "icon": "01d"}]}, {"dt": 1623164400, "temp": 300.64, "feels_like": 300.27, "pressure": 1019, "humidity": 39, "dew_point": 285.46, "clouds": 0, "visibility": 10000, "wind_speed": 1.54, "wind_deg": 0, "weather": [{"id": 800, "main": "Clear", "description": "clear sky", "icon": "01d"}]}, {"dt": 1623168000, "temp": 300.37, "feels_like": 299.44, "pressure": 1019, "humidity": 41, "dew_point": 285.98, "clouds": 0, "visibility": 10000, "wind_speed": 2.57, "wind_deg": 20, "weather": [{"id": 800, "main": "Clear", "description": "clear sky", "icon": "01d"}]}, {"dt": 1623171600, "temp": 299.26, "feels_like": 298.69, "pressure": 1019, "humidity": 47, "dew_point": 287.08, "clouds": 0, "visibility": 10000, "wind_speed": 2.57, "wind_deg": 10, "weather": [{"id": 800, "main": "Clear", "description": "clear sky", "icon": "01d"}]}, {"dt": 1623175200, "temp": 298.64, "feels_like": 297.2, "pressure": 1018, "humidity": 44, "dew_point": 285.5, "clouds": 0, "visibility": 10000, "wind_speed": 3.09, "wind_deg": 20, "weather": [{"id": 800, "main": "Clear", "description": "clear sky", "icon": "01d"}]}, {"dt": 1623178800, "temp": 296.7, "feels_like": 295.3, "pressure": 1017, "humidity": 46, "dew_point": 284.42, "clouds": 0, "visibility": 10000, "wind_speed": 2.57, "wind_deg": 60, "weather": [{"id": 800, "main": "Clear", "description": "clear sky", "icon": "01d"}]}, {"dt": 1623182400, "temp": 294.67, "feels_like": 294.07, "pressure": 1018, "humidity": 53, "dew_point": 284.7, "clouds": 0, "visibility": 10000, "wind_speed": 1.54, "wind_deg": 60, "weather": [{"id": 800, "main": "Clear", "description": "clear sky", "icon": "01n"}]}, {"dt": 1623186000, "temp": 293.05, "feels_like": 292.26, "pressure": 1020, "humidity": 56, "dew_point": 284.02, "clouds": 0, "visibility": 10000, "wind_speed": 1.54, "wind_deg": 70, "weather": [{"id": 800, "main": "Clear", "description": "clear sky", "icon": "01n"}]}, {"dt": 1623189600, "temp": 291.5, "feels_like": 290.59, "pressure": 1019, "humidity": 60, "dew_point": 283.61, "clouds": 0, "visibility": 10000, "wind_speed": 1.54, "wind_deg": 70, "weather": [{"id": 800, "main": "Clear", "description": "clear sky", "icon": "01n"}]}, {"dt": 1623193200, "temp": 290.2, "feels_like": 289.18, "pressure": 1019, "humidity": 72, "dew_point": 285.12, "clouds": 0, "visibility": 10000, "wind_speed": 2.32, "wind_deg": 96, "wind_gust": 2.46, "weather": [{"id": 800, "main": "Clear", "description": "clear sky", "icon": "01n"}]}]}