{"lat": 46.6507, "lon": 0.3748, "timezone": "Europe/Paris", "timezone_offset": 7200, "hourly": [{"dt": 1624222800, "temp": 290.28, "feels_like": 289.62, "pressure": 1006, "humidity": 60, "dew_point": 282.46, "uvi": 0, "clouds": 36, "visibility": 10000, "wind_speed": 3.51, "wind_deg": 225, "wind_gust": 8.47, "weather": [{"id": 802, "main": "Clouds", "description": "scattered clouds", "icon": "03n"}], "pop": 0.29}, {"dt": 1624226400, "temp": 289.81, "feels_like": 289.31, "pressure": 1006, "humidity": 68, "dew_point": 283.88, "uvi": 0, "clouds": 34, "visibility": 10000, "wind_speed": 3.65, "wind_deg": 216, "wind_gust": 8.84, "weather": [{"id": 802, "main": "Clouds", "description": "scattered clouds", "icon": "03n"}], "pop": 0.26}, {"dt": 1624230000, "temp": 289.08, "feels_like": 288.69, "pressure": 1007, "humidity": 75, "dew_point": 284.66, "uvi": 0, "clouds": 30, "visibility": 10000, "wind_speed": 2.8, "wind_deg": 233, "wind_gust": 5.57, "weather": [{"id": 802, "main": "Clouds", "description": "scattered clouds", "icon": "03n"}], "pop": 0.15}, {"dt": 1624233600, "temp": 288.06, "feels_like": 287.75, "pressure": 1007, "humidity": 82, "dew_point": 285.02, "uvi": 0, "clouds": 26, "visibility": 10000, "wind_speed": 2.81, "wind_deg": 204, "wind_gust": 3.93, "weather": [{"id": 802, "main": "Clouds", "description": "scattered clouds", "icon": "03n"}], "pop": 0.1}, {"dt": 1624237200, "temp": 287.1, "feels_like": 286.87, "pressure": 1008, "humidity": 89, "dew_point": 285.32, "uvi": 0, "clouds": 23, "visibility": 10000, "wind_speed": 2.32, "wind_deg": 215, "wind_gust": 2.75, "weather": [{"id": 801, "main": "Clouds", "description": "few clouds", "icon": "02n"}], "pop": 0.01}, {"dt": 1624240800, "temp": 285.94, "feels_like": 285.76, "pressure": 1008, "humidity": 95, "dew_point": 284.97, "uvi": 0, "clouds": 29, "visibility": 10000, "wind_speed": 1.58, "wind_deg": 228, "wind_gust": 1.62, "weather": [{"id": 802, "main": "Clouds", "description": "scattered clouds", "icon": "03n"}], "pop": 0}, {"dt": 1624244400, "temp": 285.65, "feels_like": 285.41, "pressure": 1007, "humidity": 94, "dew_point": 284.54, "uvi": 0, "clouds": 20, "visibility": 10000, "wind_speed": 1.01, "wind_deg": 231, "wind_gust": 1.09, "weather": [{"id": 801, "main": "Clouds", "description": "few clouds", "icon": "02n"}], "pop": 0}, {"dt": 1624248000, "temp": 285.49, "feels_like": 285.23, "pressure": 1007, "humidity": 94, "dew_point": 284.33, "uvi": 0, "clouds": 17, "visibility": 10000, "wind_speed": 0.96, "wind_deg": 192, "wind_gust": 1.01, "weather": [{"id": 801, "main": "Clouds", "description": "few clouds", "icon": "02n"}], "pop": 0}, {"dt": 1624251600, "temp": 286.26, "feels_like": 286.08, "pressure": 1007, "humidity": 94, "dew_point": 285.07, "uvi": 0.14, "clouds": 17, "visibility": 10000, "wind_speed": 0.82, "wind_deg": 185, "wind_gust": 0.89, "weather": [{"id": 500, "main": "Rain", "description": "light rain", "icon": "10d"}], "pop": 0.2, "rain": {"1h": 0.11}}, {"dt": 1624255200, "temp": 288.05, "feels_like": 287.89, "pressure": 1008, "humidity": 88, "dew_point": 285.86, "uvi": 0.49, "clouds": 18, "visibility": 10000, "wind_speed": 0.73, "wind_deg": 171, "wind_gust": 0.86, "weather": [{"id": 801, "main": "Clouds", "description": "few clouds", "icon": "02d"}], "pop": 0}, {"dt": 1624258800, "temp": 289.68, "feels_like": 289.56, "pressure": 1008, "humidity": 83, "dew_point": 286.55, "uvi": 1.12, "clouds": 8, "visibility": 10000, "wind_speed": 2.16, "wind_deg": 139, "wind_gust": 2.6, "weather": [{"id": 800, "main": "Clear", "description": "clear sky", "icon": "01d"}], "pop": 0}, {"dt": 1624262400, "temp": 291.31, "feels_like": 291.19, "pressure": 1008, "humidity": 77, "dew_point": 286.99, "uvi": 2.2, "clouds": 18, "visibility": 10000, "wind_speed": 2.6, "wind_deg": 169, "wind_gust": 3.56, "weather": [{"id": 801, "main": "Clouds", "description": "few clouds", "icon": "02d"}], "pop": 0.06}, {"dt": 1624266000, "temp": 292.76, "feels_like": 292.55, "pressure": 1008, "humidity": 68, "dew_point": 286.62, "uvi": 3.54, "clouds": 42, "visibility": 10000, "wind_speed": 2.93, "wind_deg": 200, "wind_gust": 4.29, "weather": [{"id": 802, "main": "Clouds", "description": "scattered clouds", "icon": "03d"}], "pop": 0.1}, {"dt": 1624269600, "temp": 293.97, "feels_like": 293.7, "pressure": 1008, "humidity": 61, "dew_point": 286.06, "uvi": 5.18, "clouds": 57, "visibility": 10000, "wind_speed": 3.63, "wind_deg": 210, "wind_gust": 5.57, "weather": [{"id": 803, "main": "Clouds", "description": "broken clouds", "icon": "04d"}], "pop": 0.15}, {"dt": 1624273200, "temp": 295.23, "feels_like": 294.98, "pressure": 1008, "humidity": 57, "dew_point": 286.07, "uvi": 6.22, "clouds": 58, "visibility": 10000, "wind_speed": 4.31, "wind_deg": 200, "wind_gust": 6.27, "weather": [{"id": 500, "main": "Rain", "description": "light rain", "icon": "10d"}], "pop": 0.43, "rain": {"1h": 0.27}}, {"dt": 1624276800, "temp": 296.01, "feels_like": 295.68, "pressure": 1007, "humidity": 51, "dew_point": 285.28, "uvi": 6.6, "clouds": 59, "visibility": 10000, "wind_speed": 5.43, "wind_deg": 211, "wind_gust": 7.43, "weather": [{"id": 500, "main": "Rain", "description": "light rain", "icon": "10d"}], "pop": 0.54, "rain": {"1h": 0.21}}, {"dt": 1624280400, "temp": 295.62, "feels_like": 295.28, "pressure": 1007, "humidity": 52, "dew_point": 284.92, "uvi": 5.4, "clouds": 100, "visibility": 10000, "wind_speed": 5.67, "wind_deg": 225, "wind_gust": 7.54, "weather": [{"id": 500, "main": "Rain", "description": "light rain", "icon": "10d"}], "pop": 0.56, "rain": {"1h": 0.11}}, {"dt": 1624284000, "temp": 293.69, "feels_like": 293.39, "pressure": 1008, "humidity": 61, "dew_point": 285.65, "uvi": 4.5, "clouds": 100, "visibility": 10000, "wind_speed": 3.66, "wind_deg": 232, "wind_gust": 6.42, "weather": [{"id": 500, "main": "Rain", "description": "light rain", "icon": "10d"}], "pop": 0.55, "rain": {"1h": 0.11}}, {"dt": 1624287600, "temp": 294.71, "feels_like": 294.46, "pressure": 1008, "humidity": 59, "dew_point": 286.08, "uvi": 3.28, "clouds": 84, "visibility": 10000, "wind_speed": 5.57, "wind_deg": 227, "wind_gust": 7.5, "weather": [{"id": 500, "main": "Rain", "description": "light rain", "icon": "10d"}], "pop": 0.67, "rain": {"1h": 0.26}}, {"dt": 1624291200, "temp": 294.34, "feels_like": 294.11, "pressure": 1008, "humidity": 61, "dew_point": 286.37, "uvi": 2.35, "clouds": 77, "visibility": 10000, "wind_speed": 6.47, "wind_deg": 232, "wind_gust": 7.84, "weather": [{"id": 500, "main": "Rain", "description": "light rain", "icon": "10d"}], "pop": 0.73, "rain": {"1h": 0.38}}, {"dt": 1624294800, "temp": 293.97, "feels_like": 293.7, "pressure": 1008, "humidity": 61, "dew_point": 285.94, "uvi": 1.21, "clouds": 78, "visibility": 10000, "wind_speed": 6.13, "wind_deg": 241, "wind_gust": 8.04, "weather": [{"id": 500, "main": "Rain", "description": "light rain", "icon": "10d"}], "pop": 0.73, "rain": {"1h": 0.19}}, {"dt": 1624298400, "temp": 293.56, "feels_like": 293.28, "pressure": 1008, "humidity": 62, "dew_point": 285.98, "uvi": 0.48, "clouds": 68, "visibility": 10000, "wind_speed": 4.77, "wind_deg": 241, "wind_gust": 7.06, "weather": [{"id": 803, "main": "Clouds", "description": "broken clouds", "icon": "04d"}], "pop": 0.67}, {"dt": 1624302000, "temp": 291.53, "feels_like": 291.28, "pressure": 1009, "humidity": 71, "dew_point": 286.04, "uvi": 0.15, "clouds": 17, "visibility": 10000, "wind_speed": 4.25, "wind_deg": 236, "wind_gust": 7.57, "weather": [{"id": 801, "main": "Clouds", "description": "few clouds", "icon": "02d"}], "pop": 0.44}, {"dt": 1624305600, "temp": 288.65, "feels_like": 288.45, "pressure": 1010, "humidity": 84, "dew_point": 285.75, "uvi": 0, "clouds": 37, "visibility": 10000, "wind_speed": 3.59, "wind_deg": 239, "wind_gust": 7.33, "weather": [{"id": 500, "main": "Rain", "description": "light rain", "icon": "10n"}], "pop": 0.49, "rain": {"1h": 0.32}}, {"dt": 1624309200, "temp": 287.51, "feels_like": 287.33, "pressure": 1011, "humidity": 89, "dew_point": 285.61, "uvi": 0, "clouds": 56, "visibility": 10000, "wind_speed": 2.76, "wind_deg": 244, "wind_gust": 4.44, "weather": [{"id": 500, "main": "Rain", "description": "light rain", "icon": "10n"}], "pop": 0.54, "rain": {"1h": 0.12}}, {"dt": 1624312800, "temp": 287.04, "feels_like": 286.89, "pressure": 1011, "humidity": 92, "dew_point": 285.62, "uvi": 0, "clouds": 67, "visibility": 10000, "wind_speed": 2.7, "wind_deg": 241, "wind_gust": 3.89, "weather": [{"id": 500, "main": "Rain", "description": "light rain", "icon": "10n"}], "pop": 0.45, "rain": {"1h": 0.39}}, {"dt": 1624316400, "temp": 286.88, "feels_like": 286.74, "pressure": 1011, "humidity": 93, "dew_point": 285.6, "uvi": 0, "clouds": 73, "visibility": 10000, "wind_speed": 2.65, "wind_deg": 224, "wind_gust": 4.18, "weather": [{"id": 803, "main": "Clouds", "description": "broken clouds", "icon": "04n"}], "pop": 0.35}, {"dt": 1624320000, "temp": 286.42, "feels_like": 286.26, "pressure": 1011, "humidity": 94, "dew_point": 285.31, "uvi": 0, "clouds": 78, "visibility": 10000, "wind_speed": 2.53, "wind_deg": 201, "wind_gust": 2.89, "weather": [{"id": 803, "main": "Clouds", "description": "broken clouds", "icon": "04n"}], "pop": 0.35}, {"dt": 1624323600, "temp": 286.26, "feels_like": 286.11, "pressure": 1011, "humidity": 95, "dew_point": 285.22, "uvi": 0, "clouds": 100, "visibility": 10000, "wind_speed": 2.82, "wind_deg": 190, "wind_gust": 4.25, "weather": [{"id": 804, "main": "Clouds", "description": "overcast clouds", "icon": "04n"}], "pop": 0.05}, {"dt": 1624327200, "temp": 285.93, "feels_like": 285.74, "pressure": 1011, "humidity": 95, "dew_point": 284.95, "uvi": 0, "clouds": 99, "visibility": 10000, "wind_speed": 2.57, "wind_deg": 198, "wind_gust": 3.88, "weather": [{"id": 804, "main": "Clouds", "description": "overcast clouds", "icon": "04n"}], "pop": 0.04}, {"dt": 1624330800, "temp": 285.79, "feels_like": 285.59, "pressure": 1011, "humidity": 95, "dew_point": 284.81, "uvi": 0, "clouds": 99, "visibility": 10000, "wind_speed": 2.38, "wind_deg": 195, "wind_gust": 3.54, "weather": [{"id": 804, "main": "Clouds", "description": "overcast clouds", "icon": "04n"}], "pop": 0.02}, {"dt": 1624334400, "temp": 285.71, "feels_like": 285.5, "pressure": 1011, "humidity": 95, "dew_point": 284.77, "uvi": 0, "clouds": 100, "visibility": 10000, "wind_speed": 2.35, "wind_deg": 186, "wind_gust": 3.37, "weather": [{"id": 804, "main": "Clouds", "description": "overcast clouds", "icon": "04n"}], "pop": 0.02}, {"dt": 1624338000, "temp": 286.23, "feels_like": 286.07, "pressure": 1012, "humidity": 95, "dew_point": 285.21, "uvi": 0.14, "clouds": 100, "visibility": 10000, "wind_speed": 2.25, "wind_deg": 170, "wind_gust": 4.43, "weather": [{"id": 804, "main": "Clouds", "description": "overcast clouds", "icon": "04d"}], "pop": 0.04}, {"dt": 1624341600, "temp": 287.59, "feels_like": 287.47, "pressure": 1012, "humidity": 91, "dew_point": 285.99, "uvi": 0.52, "clouds": 100, "visibility": 10000, "wind_speed": 2.7, "wind_deg": 173, "wind_gust": 4.56, "weather": [{"id": 804, "main": "Clouds", "description": "overcast clouds", "icon": "04d"}], "pop": 0.06}, {"dt": 1624345200, "temp": 288.96, "feels_like": 288.87, "pressure": 1012, "humidity": 87, "dew_point": 286.67, "uvi": 1.28, "clouds": 95, "visibility": 10000, "wind_speed": 3.24, "wind_deg": 175, "wind_gust": 4.28, "weather": [{"id": 804, "main": "Clouds", "description": "overcast clouds", "icon": "04d"}], "pop": 0.06}, {"dt": 1624348800, "temp": 290.56, "feels_like": 290.45, "pressure": 1012, "humidity": 80, "dew_point": 286.98, "uvi": 2.5, "clouds": 91, "visibility": 10000, "wind_speed": 3.38, "wind_deg": 171, "wind_gust": 4.01, "weather": [{"id": 804, "main": "Clouds", "description": "overcast clouds", "icon": "04d"}], "pop": 0.09}, {"dt": 1624352400, "temp": 291.93, "feels_like": 291.8, "pressure": 1012, "humidity": 74, "dew_point": 286.96, "uvi": 4.01, "clouds": 85, "visibility": 10000, "wind_speed": 3.22, "wind_deg": 167, "wind_gust": 3.56, "weather": [{"id": 500, "main": "Rain", "description": "light rain", "icon": "10d"}], "pop": 0.59, "rain": {"1h": 0.41}}, {"dt": 1624356000, "temp": 292.45, "feels_like": 292.34, "pressure": 1012, "humidity": 73, "dew_point": 287.32, "uvi": 4.94, "clouds": 81, "visibility": 7501, "wind_speed": 3.52, "wind_deg": 178, "wind_gust": 3.74, "weather": [{"id": 501, "main": "Rain", "description": "moderate rain", "icon": "10d"}], "pop": 0.92, "rain": {"1h": 1.11}}, {"dt": 1624359600, "temp": 292.7, "feels_like": 292.62, "pressure": 1012, "humidity": 73, "dew_point": 287.53, "uvi": 5.92, "clouds": 83, "visibility": 7845, "wind_speed": 3.56, "wind_deg": 191, "wind_gust": 3.66, "weather": [{"id": 501, "main": "Rain", "description": "moderate rain", "icon": "10d"}], "pop": 0.94, "rain": {"1h": 1.41}}, {"dt": 1624363200, "temp": 292.96, "feels_like": 292.88, "pressure": 1012, "humidity": 72, "dew_point": 287.49, "uvi": 6.28, "clouds": 86, "visibility": 10000, "wind_speed": 3.44, "wind_deg": 210, "wind_gust": 3.54, "weather": [{"id": 501, "main": "Rain", "description": "moderate rain", "icon": "10d"}], "pop": 0.98, "rain": {"1h": 1.23}}, {"dt": 1624366800, "temp": 293.4, "feels_like": 293.28, "pressure": 1012, "humidity": 69, "dew_point": 287.45, "uvi": 6.53, "clouds": 98, "visibility": 10000, "wind_speed": 3.08, "wind_deg": 233, "wind_gust": 3.35, "weather": [{"id": 500, "main": "Rain", "description": "light rain", "icon": "10d"}], "pop": 0.96, "rain": {"1h": 0.76}}, {"dt": 1624370400, "temp": 294.09, "feels_like": 293.91, "pressure": 1012, "humidity": 64, "dew_point": 286.99, "uvi": 5.44, "clouds": 99, "visibility": 10000, "wind_speed": 2.85, "wind_deg": 257, "wind_gust": 3.17, "weather": [{"id": 500, "main": "Rain", "description": "light rain", "icon": "10d"}], "pop": 0.96, "rain": {"1h": 0.25}}, {"dt": 1624374000, "temp": 294.35, "feels_like": 294.2, "pressure": 1012, "humidity": 64, "dew_point": 287.02, "uvi": 3.96, "clouds": 99, "visibility": 10000, "wind_speed": 3.44, "wind_deg": 274, "wind_gust": 3.82, "weather": [{"id": 500, "main": "Rain", "description": "light rain", "icon": "10d"}], "pop": 1, "rain": {"1h": 0.5}}, {"dt": 1624377600, "temp": 293.84, "feels_like": 293.74, "pressure": 1013, "humidity": 68, "dew_point": 287.51, "uvi": 2.57, "clouds": 98, "visibility": 10000, "wind_speed": 4.1, "wind_deg": 285, "wind_gust": 4.53, "weather": [{"id": 500, "main": "Rain", "description": "light rain", "icon": "10d"}], "pop": 1, "rain": {"1h": 0.72}}, {"dt": 1624381200, "temp": 292.78, "feels_like": 292.78, "pressure": 1013, "humidity": 76, "dew_point": 288.33, "uvi": 1.32, "clouds": 97, "visibility": 10000, "wind_speed": 4.27, "wind_deg": 293, "wind_gust": 5.27, "weather": [{"id": 500, "main": "Rain", "description": "light rain", "icon": "10d"}], "pop": 1, "rain": {"1h": 0.89}}, {"dt": 1624384800, "temp": 291.91, "feels_like": 292.01, "pressure": 1014, "humidity": 83, "dew_point": 288.69, "uvi": 0.52, "clouds": 96, "visibility": 10000, "wind_speed": 3.91, "wind_deg": 297, "wind_gust": 5.73, "weather": [{"id": 500, "main": "Rain", "description": "light rain", "icon": "10d"}], "pop": 1, "rain": {"1h": 0.72}}, {"dt": 1624388400, "temp": 290.6, "feels_like": 290.7, "pressure": 1014, "humidity": 88, "dew_point": 288.36, "uvi": 0.15, "clouds": 79, "visibility": 10000, "wind_speed": 3.14, "wind_deg": 300, "wind_gust": 5.49, "weather": [{"id": 500, "main": "Rain", "description": "light rain", "icon": "10d"}], "pop": 0.78, "rain": {"1h": 0.16}}, {"dt": 1624392000, "temp": 288.58, "feels_like": 288.61, "pressure": 1015, "humidity": 93, "dew_point": 287.29, "uvi": 0, "clouds": 63, "visibility": 10000, "wind_speed": 2.92, "wind_deg": 297, "wind_gust": 4.6, "weather": [{"id": 500, "main": "Rain", "description": "light rain", "icon": "10n"}], "pop": 0.7, "rain": {"1h": 0.13}}]}